{"players":[{"name":"Mason Graham","team":"Giants"},{"name":"Will Johnson","team":"Raiders"},{"name":"Travis Hunter","team":"Jaguars"},{"name":"Luther Burden","team":"Patriots"},{"name":"James Pearce","team":"Panthers"},{"name":"Kelvin Banks","team":"Browns"},{"name":"Will Campbell","team":"Jets"},{"name":"J.T. Tuimoloau","team":"Titans"},{"name":"Tre Harris","team":"Bengals"},{"name":"Emery jones","team":"Bears"},{"name":"Shedeur Sanders","team":"Saints"},{"name":"Derrick Moore","team":"Dolphins"},{"name":"Denzel Burke","team":"Cowboys"},{"name":"Blake Miller","team":"49ers"},{"name":"Benjamin Morrison","team":"Colts"},{"name":"Jack Sawyer","team":"Rams"},{"name":"Deone Walker","team":"Buccaneers"},{"name":"Dani Denni","team":"Cardinals"},{"name":"Jeremiah Alexander","team":"Falcons"},{"name":"Carson Beck","team":"Seahawks"},{"name":"Tetairoa McMillan","team":"Broncos"},{"name":"Princely Umanmielen","team":"Texans"},{"name":"Ashton Jeanty","team":"Commanders"},{"name":"Nic Scourton","team":"Ravens"},{"name":"Abdul Carter","team":"Chargers"},{"name":"Drew Shelton","team":"Packers"},{"name":"Cam Miller","team":"Steelers"},{"name":"Nazir Stackhouse","team":"Eagles"},{"name":"Kenneth Grant","team":"Vikings"},{"name":"Jacob Sexton","team":"Bills"},{"name":"Wyatt Milum","team":"Chiefs"},{"name":"Barion Brown","team":"Lions"},{"name":"TreVeyon Henderson","team":"Giants"},{"name":"Tyler Booker","team":"Raiders"},{"name":"Walter Nolen","team":"Jaguars"},{"name":"Reuben Fatheree II","team":"Patriots"},{"name":"Dasan McCullough","team":"Bears"},{"name":"Tyleik Williams","team":"Browns"},{"name":"Emeka Egbuka","team":"Jets"},{"name":"Marques Cox","team":"Titans"},{"name":"Parker Brailsford","team":"Bengals"},{"name":"Dontay Corleone","team":"Bears"},{"name":"Evan Stewart","team":"Saints"},{"name":"Mansoor Delane","team":"Dolphins"},{"name":"Ollie Gordon","team":"Cowboys"},{"name":"Harold Perkins","team":"49ers"},{"name":"Juice Wells","team":"Colts"},{"name":"Davison Igbinosun","team":"Panthers"},{"name":"Jason Marshall","team":"Buccaneers"},{"name":"Antonio Williams","team":"Cardinals"},{"name":"Bear Alexander","team":"Falcons"},{"name":"DJ Campbell","team":"Seahawks"},{"name":"Mykel Williams","team":"Broncos"},{"name":"Isaiah Bond","team":"Texans"},{"name":"Malaki Starks","team":"Commanders"},{"name":"Quinshon Judkins","team":"Ravens"},{"name":"Tory Horton","team":"Chargers"},{"name":"Jacob Parrish","team":"Packers"},{"name":"Danny Stutsman","team":"Steelers"},{"name":"Trey Moore","team":"Eagles"},{"name":"Dane Key","team":"Bills"},{"name":"Howard Cross III","team":"Bills"},{"name":"Colston Loveland","team":"Chiefs"},{"name":"David Bailey","team":"Lions"},{"name":"Quinn Ewers","team":"Giants"},{"name":"Jaxson Dart","team":"Raiders"},{"name":"Luke Lachey","team":"Jaguars"},{"name":"Barrett Carter","team":"Patriots"},{"name":"Benjamin Yurosek","team":"Panthers"},{"name":"Donovan Jackson","team":"Browns"},{"name":"Nick Singleton","team":"Raiders"},{"name":"John Pius","team":"Chiefs"},{"name":"Jahdae Barron","team":"Bengals"},{"name":"Smael Mondon","team":"Bears"},{"name":"Nick Emmanwori","team":"Saints"},{"name":"Malachi Moore","team":"Commanders"},{"name":"Anthony Belton","team":"Cowboys"},{"name":"Colbie Young","team":"49ers"},{"name":"RJ Oben","team":"Colts"},{"name":"Jalen Milroe","team":"Rams"},{"name":"Conner Weigman","team":"Buccaneers"},{"name":"Zach Rice","team":"Cardinals"},{"name":"AJ Cornelius","team":"Patriots"},{"name":"Earnest Greene","team":"Seahawks"},{"name":"Davin Vann","team":"Broncos"},{"name":"TJ Sanders","team":"Texans"},{"name":"Alfred Collins","team":"Saints"},{"name":"Jonathan Mendoza","team":"Ravens"},{"name":"Aaron Graves","team":"Chargers"},{"name":"Clay Webb","team":"Packers"},{"name":"Lathan Ransom","team":"Steelers"},{"name":"Xavier Nwakpa","team":"Eagles"},{"name":"Shemar James","team":"Jaguars"},{"name":"Ashton Gillotte","team":"Browns"},{"name":"Omarion Hampton","team":"Chiefs"},{"name":"Keon Sabb","team":"Jets"},{"name":"Jalen Travis","team":"Vikings"},{"name":"John Campbell Jr.","team":"Dolphins"},{"name":"Oscar Delp","team":"Dolphins"},{"name":"Tez Johnson","team":"Rams"},{"name":"Tate Ratledge","team":"49ers"},{"name":"Joshua Gray","team":"Giants"},{"name":"Jake Briningstool","team":"Raiders"},{"name":"Josaiah Stewart","team":"Jaguars"},{"name":"Jaydn Ott","team":"Patriots"},{"name":"Omar Norma","team":"Panthers"},{"name":"Xavier Restrepo","team":"Browns"},{"name":"Domani Jackson","team":"Jets"},{"name":"Cameron Ward","team":"Titans"},{"name":"Donovan Edwards","team":"Bengals"},{"name":"Damien Martinez","team":"Bills"},{"name":"Bryson Nesbit","team":"Saints"},{"name":"J. Michael Sturdivant","team":"Dolphins"},{"name":"Marcus Mbow","team":"Panthers"},{"name":"JQ Hardaway","team":"49ers"},{"name":"Rod Moore","team":"Colts"},{"name":"Jamon Duma","team":"Rams"},{"name":"Germie Bernard","team":"Buccaneers"},{"name":"Zy Alexander","team":"Cardinals"},{"name":"Trey Amos","team":"Falcons"},{"name":"Maxwell Hairston","team":"Titans"},{"name":"Tyler Baron","team":"Broncos"},{"name":"Caden Prieskorn","team":"Texans"},{"name":"Ty Hamilton","team":"Saints"},{"name":"Quincy Riley","team":"Ravens"},{"name":"Raheim Sanders","team":"Chargers"},{"name":"Collin Oliver","team":"Packers"},{"name":"Jasheen Davis","team":"Steelers"},{"name":"Deion Burks","team":"Eagles"},{"name":"Thor Griffith","team":"Jaguars"},{"name":"Trey Zuhn","team":"Bills"},{"name":"Tim Smith","team":"Chiefs"},{"name":"Fentrell Cypress","team":"Lions"},{"name":"Jeremiah Hunter","team":"Giants"},{"name":"Sonny Styles","team":"Ravens"},{"name":"Akheem Mesidor","team":"Seahawks"},{"name":"Eric Ayomanor","team":"Bills"},{"name":"Jason Henderson","team":"Panthers"},{"name":"Jay Higgins","team":"Raiders"},{"name":"Trevor Etienne","team":"Jaguars"},{"name":"Bryce Anderson","team":"Patriots"},{"name":"Jalon Walker","team":"Panthers"},{"name":"Sebastian Castro","team":"Vikings"},{"name":"Devin Neal","team":"Jets"},{"name":"Billy Bowman","team":"Titans"},{"name":"Lander Barton","team":"Bengals"},{"name":"Trevor Keegan","team":"Bears"},{"name":"Xavier Watts","team":"Commanders"},{"name":"Riley Leonard","team":"Dolphins"},{"name":"Bru McCoy","team":"Cowboys"},{"name":"Jacoby Mathews","team":"49ers"},{"name":"RJ Maryland","team":"Colts"},{"name":"Xavier Guillory","team":"Steelers"},{"name":"Steve Linton","team":"Buccaneers"},{"name":"Tai Felton","team":"Cardinals"},{"name":"Patrick Payton","team":"Giants"},{"name":"Jager Burton","team":"Dolphins"},{"name":"Xavian Sorey","team":"Eagles"},{"name":"Tyler Warren","team":"Eagles"},{"name":"Kyren Lacy","team":"Panthers"},{"name":"Brant Kuithe","team":"Chargers"},{"name":"LT Overton","team":"Packers"},{"name":"Andrew Mukuba","team":"Jets"},{"name":"Julian Fleming","team":"Eagles"},{"name":"Kamari Ramsey","team":"Vikings"},{"name":"Matthew Golden","team":"Texans"},{"name":"J.J. Weaver","team":"Titans"},{"name":"KJ Winston","team":"Browns"},{"name":"Will Howard","team":"Cowboys"},{"name":"Sean Martin","team":"Bills"},{"name":"Major Burns","team":"Cowboys"},{"name":"Jeadyn Lukus","team":"Cowboys"},{"name":"Nic Anderson","team":"Ravens"},{"name":"Torricelli Simpkins III","team":"49ers"},{"name":"Harold Fannin","team":"Seahawks"},{"name":"Jack Nelson","team":"Bills"},{"name":"Myles Hinton","team":"Raiders"},{"name":"Jacolby Spells","team":"Jaguars"},{"name":"Ben Bywater","team":"Chargers"},{"name":"Oronde Gadsden","team":"Ravens"},{"name":"Dorian Strong","team":"Browns"},{"name":"Garrett Nussmeier","team":"Jets"},{"name":"Aubrey Burks","team":"Titans"},{"name":"Zykeivous Walker","team":"Bengals"},{"name":"Jared Ivey","team":"Seahawks"},{"name":"Tacario Davis","team":"Saints"},{"name":"Jared Wilson","team":"Browns"},{"name":"Vega Ioane","team":"Cowboys"},{"name":"Savion Williams","team":"49ers"},{"name":"Micah Pettus","team":"Colts"},{"name":"Jonah Monheim","team":"Rams"},{"name":"Shemar Stewart","team":"Lions"},{"name":"Kyle Kennard","team":"Broncos"},{"name":"Bud Clark","team":"Rams"},{"name":"Cameron Williams","team":"Jaguars"},{"name":"Gavin Bartholomew","team":"Broncos"},{"name":"Jack Howell","team":"Rams"},{"name":"Jalen Catalon","team":"Commanders"},{"name":"Rylie Mills","team":"Ravens"},{"name":"Justus Ros","team":"Chargers"},{"name":"Justin Walley","team":"Packers"},{"name":"Roman Hemby","team":"Bears"},{"name":"Deontae Lawson","team":"Broncos"},{"name":"Adam Randall","team":"Browns"},{"name":"Eli Cox","team":"Bills"},{"name":"Airentae Ersery","team":"Jets"},{"name":"Kobe Prentice","team":"Bills"},{"name":"Mason Taylor","team":"Chargers"},{"name":"Xavier Truss","team":"Raiders"},{"name":"Justin Flowe","team":"Cowboys"},{"name":"Cole Hutson","team":"Ravens"},{"name":"Jayden Bray","team":"Ravens"},{"name":"Landon Jackson","team":"Chargers"},{"name":"Chico Bennett Jr.","team":"Raiders"},{"name":"Ja'Travis Broughton","team":"Chargers"},{"name":"Azareyeh Thomas","team":"Giants"},{"name":"Jordan James","team":"Raiders"},{"name":"Seth McLaughlin","team":"Jaguars"},{"name":"Malachi Fields","team":"Patriots"},{"name":"Dylan Fairchild","team":"Cardinals"},{"name":"Jermari Harris","team":"Chargers"},{"name":"Kaden Prather","team":"Chiefs"},{"name":"Jaheim Singletary","team":"Patriots"},{"name":"Jyaire Brown","team":"Bears"},{"name":"Marvin Jones Jr.","team":"Dolphins"},{"name":"Fa'Alili Fa'amoe","team":"Steelers"},{"name":"Jake Majors","team":"Dolphins"},{"name":"Ty French","team":"Lions"},{"name":"Tahj Brooks","team":"Panthers"},{"name":"Bradyn Swinson","team":"Colts"},{"name":"Mason Richman","team":"Falcons"},{"name":"Jayden McGowan","team":"Buccaneers"},{"name":"CJ Dippre","team":"49ers"},{"name":"Jalon Daniels","team":"Packers"},{"name":"Kobe Hudson","team":"Seahawks"},{"name":"Patrick Jenkins","team":"Commanders"},{"name":"Ben Scott","team":"Texans"},{"name":"Kamari Wilson","team":"Commanders"},{"name":"Brady Cook","team":"Ravens"},{"name":"Kaimon Rucker","team":"Patriots"},{"name":"Jayden Higgins","team":"Titans"},{"name":"De'Corian Clark","team":"Vikings"},{"name":"Kaytron Allen","team":"Commanders"},{"name":"Derrick Harmon","team":"Bears"},{"name":"Jabbar Muhammed","team":"Giants"},{"name":"Robert Scott Jr.","team":"Cowboys"},{"name":"Drew Allar","team":"Lions"},{"name":"Le'Veon Moss","team":"Packers"},{"name":"Nick Martin","team":"49ers"},{"name":"Connor Colby","team":"Browns"},{"name":"Tony Grimes","team":"Browns"},{"name":"Ja'corey Brooks","team":"Dolphins"},{"name":"Dominic Lovett","team":"Chiefs"},{"name":"Brandon Crensha","team":"Saints"},{"name":"Korey Foreman","team":"Chiefs"}],"pickedFor":"Commanders"}