{
  "players": [
    { "name": "Caleb Williams", "team": "CHI" },
    { "name": "Jayden Daniels", "team": "WAS" },
    { "name": "Marvin Harrison Jr", "team": "NE" },
    { "name": "Rome Odunze", "team": "ARI" },
    { "name": "Brock Bowers", "team": "LAC" },
    { "name": "Malik Nabers", "team": "NYG" },
    { "name": "Drake Maye", "team": "DEN" },
    { "name": "Joe Alt", "team": "LV" },
    { "name": "Chop Robinson", "team": "CHI" },
    { "name": "Dallas Turner", "team": "NYJ" },
    { "name": "Quinyon Mitchell", "team": "MIN" },
    { "name": "Olumuyiwa Fashanu", "team": "TEN" },
    { "name": "Byron Murphy II", "team": "ATL" },
    { "name": "Kingsley Suamataia", "team": "NO" },
    { "name": "Terrion Arnold", "team": "IND" },
    { "name": "Kool-Aid McKinstry", "team": "SEA" },
    { "name": "Brian Thomas Jr.", "team": "JAX" },
    { "name": "Taliese Fuaga", "team": "CIN" },
    { "name": "Jared Verse", "team": "LAR" },
    { "name": "Tyler Guyton", "team": "PIT" },
    { "name": "Amarius Mims", "team": "MIA" },
    { "name": "Adonai Mitchell", "team": "PHI" },
    { "name": "J.J. McCarthy", "team": "MIN" },
    { "name": "JC Latham", "team": "DAL" },
    { "name": "Troy Fautanu", "team": "BAL" },
    { "name": "Laiatu Latu", "team": "TB" },
    { "name": "Graham Barton", "team": "ARI" },
    { "name": "Xavier Worthy", "team": "BUF" },
    { "name": "Cooper DeJean", "team": "DET" },
    { "name": "Jordan Morgan", "team": "GB" },
    { "name": "Nate Wiggins", "team": "SF" },
    { "name": "Devontez Walker", "team": "KC" },
    { "name": "Troy Franklin", "team": "CAR" },
    { "name": "Jer'Zhan Newton", "team": "ARI" },
    { "name": "Bo Nix", "team": "NE" },
    { "name": "Kamari Lassiter", "team": "WAS" },
    { "name": "Ladd McConkey", "team": "LAC" },
    { "name": "Jackson Powers-Johnson", "team": "TEN" },
    { "name": "Isaiah Adams", "team": "CAR" },
    { "name": "Christian Haynes", "team": "WAS" },
    { "name": "DeWayne Carter", "team": "GB" },
    { "name": "Ennis Rakestraw Jr.", "team": "HOU" },
    { "name": "Darius Robinson", "team": "ATL" },
    { "name": "Roger Rosengarten", "team": "KC" },
    { "name": "Junior Colson", "team": "NO" },
    { "name": "Michael Penix Jr.", "team": "LV" },
    { "name": "Ja'Tavion Sanders", "team": "NYG" },
    { "name": "Khyree Jackson", "team": "JAX" },
    { "name": "Jalen McMillan", "team": "CIN" },
    { "name": "Calen Bullock", "team": "PHI" },
    { "name": "T.J. Tampa", "team": "PIT" },
    { "name": "T'Vondre Sweat", "team": "CLE" },
    { "name": "Chris Braswell", "team": "DET" },
    { "name": "Keon Coleman", "team": "LAR" },
    { "name": "Bralen Trice", "team": "MIA" },
    { "name": "Payton Wilson", "team": "DAL" },
    { "name": "McKinnley Jackson", "team": "CIN" },
    { "name": "Javon Bullard", "team": "GB" },
    { "name": "Kris Jenkins", "team": "HOU" },
    { "name": "Zak Zinter", "team": "BUF" },
    { "name": "Cooper Beebe", "team": "PHI" },
    { "name": "Adisa Isaac", "team": "GB" },
    { "name": "Johnny Wilson", "team": "SF" },
    { "name": "Roman Wilson", "team": "ATL" },
    { "name": "Patrick Paul", "team": "CAR" },
    { "name": "Caelen Carson", "team": "ARI" },
    { "name": "Beau Brade", "team": "WAS" },
    { "name": "Marshawn Kneeland", "team": "NE" },
    { "name": "Trey Benson", "team": "LAC" },
    { "name": "Brandon Dorlus", "team": "NYG" },
    { "name": "Ben Sinnott", "team": "ARI" },
    { "name": "Ja'Lynn Polk", "team": "NYJ" },
    { "name": "Trevin Wallace", "team": "DET" },
    { "name": "D.J. James", "team": "ATL" },
    { "name": "Xavier Legette", "team": "CHI" },
    { "name": "Tyler Davis", "team": "TEN" },
    { "name": "Javion Cohen", "team": "IND" },
    { "name": "Matt Goncalves", "team": "WAS" },
    { "name": "Ruke Orhorhoro", "team": "MIN" },
    { "name": "Kris Abrams-Draine", "team": "TB" },
    { "name": "Cedric Gray", "team": "SEA" },
    { "name": "Kiran Amegadjie", "team": "IND" },
    { "name": "Edgerrin Cooper", "team": "LAR" },
    { "name": "Jermaine Burton", "team": "PIT" },
    { "name": "Ty'Ron Hopper", "team": "CLE" },
    { "name": "Cole Bishop", "team": "HOU" },
    { "name": "Jaden Hicks", "team": "BUF" },
    { "name": "Layden Robinson", "team": "GB" },
    { "name": "Brandon Coleman", "team": "TB" },
    { "name": "Jonah Elliss", "team": "ARI" },
    { "name": "Jase McClellan", "team": "GB" },
    { "name": "Zach Frazier", "team": "TB" },
    { "name": "Leonard Taylor", "team": "BAL" },
    { "name": "Javon Foster", "team": "SF" },
    { "name": "Nehemiah Pritchett", "team": "KC" },
    { "name": "Jonathon Brooks", "team": "JAX" },
    { "name": "Tory Taylor", "team": "TB" },
    { "name": "Charles Turner", "team": "PIT" },
    { "name": "Qwan'tez Stiggers", "team": "LAR" },
    { "name": "Javon Solomon", "team": "WAS" },
    { "name": "Mason McCormick", "team": "CAR" },
    { "name": "Theo Johnson", "team": "SEA" },
    { "name": "Ricky Pearsall", "team": "NE" },
    { "name": "Spencer Rattler", "team": "NE" },
    { "name": "Bucky Irving", "team": "LAC" },
    { "name": "Curtis Jacobs", "team": "PHI" },
    { "name": "Delmar Glaze", "team": "NYJ" },
    { "name": "Austin Booker", "team": "ATL" },
    { "name": "James Williams", "team": "ATL" },
    { "name": "Mehki Wingo", "team": "LAC" },
    { "name": "Josh Newton", "team": "TEN" },
    { "name": "Blake Corum", "team": "LV" },
    { "name": "Mason Smith", "team": "BAL" },
    { "name": "Decamerion Richardson", "team": "JAX" },
    { "name": "Sataoa Laumea", "team": "CIN" },
    { "name": "Ainias Smith", "team": "JAX" },
    { "name": "Malachi Corley", "team": "IND" },
    { "name": "Jeremiah Trotter Jr.", "team": "SEA" },
    { "name": "MarShawn Lloyd", "team": "NYG" },
    { "name": "Sedrick Van Pran", "team": "PIT" },
    { "name": "Will Shipley", "team": "DEN" },
    { "name": "Kingsley Eguakun", "team": "CHI" },
    { "name": "Cade Stover", "team": "HOU" },
    { "name": "Christian Jones", "team": "SF" },
    { "name": "Cornelius Johnson", "team": "TB" },
    { "name": "Malik Mustapha", "team": "GB" },
    { "name": "Chau Smith-Wade", "team": "HOU" },
    { "name": "Tylan Grable", "team": "DAL" },
    { "name": "Tommy Eichenberg", "team": "ATL" },
    { "name": "Trevor Keegan", "team": "BAL" },
    { "name": "Mike Sainristil", "team": "NE" },
    { "name": "Andru Phillips", "team": "SF" },
    { "name": "Jaylan Ford", "team": "DAL" },
    { "name": "Tyler Nubin", "team": "NYJ" },
    { "name": "Steele Chambers", "team": "KC" },
    { "name": "Cedric Johnson", "team": "DEN" },
    { "name": "Andrew Coker", "team": "SF" },
    { "name": "Johnny Dixon", "team": "ARI" },
    { "name": "Michael Hall Jr.", "team": "DET" },
    { "name": "Ray Davis", "team": "LAC" },
    { "name": "Jaylin Simpson", "team": "CAR" },
    { "name": "Nelson Ceaser", "team": "CAR" },
    { "name": "Braden Fiske", "team": "ATL" },
    { "name": "Dominique Hampton", "team": "DAL" },
    { "name": "Jaylen Wright", "team": "DEN" },
    { "name": "LaDarius Henderson", "team": "TEN" },
    { "name": "Jamari Thrash", "team": "DEN" },
    { "name": "Jordan Jefferson", "team": "JAX" },
    { "name": "Marcellas Dial", "team": "CIN" },
    { "name": "Trente Jones", "team": "NO" },
    { "name": "Khristian Boyd", "team": "NO" },
    { "name": "Michael Pratt", "team": "WAS" },
    { "name": "Brenden Rice", "team": "LV" },
    { "name": "Jarius Monroe", "team": "LAR" },
    { "name": "Gabriel Murphy", "team": "LAR" },
    { "name": "Jaylen Harrell", "team": "LAR" },
    { "name": "Marcus Rosemy-Jacksaint", "team": "BAL" },
    { "name": "Marist Liufau", "team": "MIA" },
    { "name": "Tanor Bortolini", "team": "DAL" },
    { "name": "Isaiah Davis", "team": "BUF" },
    { "name": "Devaughn Vele", "team": "NYG" },
    { "name": "Kalen King", "team": "NYG" },
    { "name": "Devin Culp", "team": "BUF" },
    { "name": "KT Leveston", "team": "WAS" },
    { "name": "Edefuan Ulofoshio", "team": "GB" },
    { "name": "Malik Washington", "team": "ARI" },
    { "name": "Tip Reiman", "team": "ATL" },
    { "name": "Max Melton", "team": "IND" },
    { "name": "Devin Leary", "team": "MIN" },
    { "name": "Dylan McMahon", "team": "NO" },
    { "name": "Tarheeb Still", "team": "LAC" },
    { "name": "Dadrion Taylor-Demerson", "team": "PHI" },
    { "name": "Myles Harden", "team": "KC" },
    { "name": "Cam Hart", "team": "KC" },
    { "name": "David Ugwoegbu", "team": "NO" },
    { "name": "Joshua Karty", "team": "SF" },
    { "name": "Myles Cole", "team": "MIN" },
    { "name": "Josiah Ezirim", "team": "PIT" },
    { "name": "Beaux Limmer", "team": "SEA" },
    { "name": "Logan Lee", "team": "SF" },
    { "name": "Ro Torrence", "team": "PHI" },
    { "name": "Garret Greenfield", "team": "TEN" },
    { "name": "Jha'Quan Jackson", "team": "NYG" },
    { "name": "C.J. Hanson", "team": "MIA" },
    { "name": "Blake Fisher", "team": "NYG" },
    { "name": "Ryan Flournoy", "team": "ARI" },
    { "name": "Jaheim Bell", "team": "ATL" },
    { "name": "Keaton Bills", "team": "HOU" },
    { "name": "Darius Muasau", "team": "HOU" },
    { "name": "Audric Estime", "team": "IND" },
    { "name": "Deantre Prince", "team": "IND" },
    { "name": "JD Bertrand", "team": "SEA" },
    { "name": "Rasheen Ali", "team": "NE" },
    { "name": "Eyabi Okie-Anoma", "team": "BUF" },
    { "name": "Andrew Raym", "team": "PIT" },
    { "name": "Jacob Cowing", "team": "LAR" },
    { "name": "Dylan Laube", "team": "ATL" },
    { "name": "Jarrett Kingston", "team": "MIA" },
    { "name": "Dominick Puni", "team": "NO" },
    { "name": "Gottlieb Ayedze", "team": "CIN" },
    { "name": "Myles Murphy", "team": "WAS" },
    { "name": "Cody Schrader", "team": "GB" },
    { "name": "Tyrone Tracy Jr.", "team": "DEN" },
    { "name": "Anthony Gould", "team": "BUF" },
    { "name": "Christian Mahogany", "team": "WAS" },
    { "name": "Caedan Wallace", "team": "CLE" },
    { "name": "Dwight McGlothern", "team": "DEN" },
    { "name": "Jared Wiley", "team": "LV" },
    { "name": "Nathaniel Watson", "team": "LAR" },
    { "name": "Marcus Harris", "team": "TEN" },
    { "name": "Brennan Jackson", "team": "NE" },
    { "name": "Keith Randolph", "team": "JAX" },
    { "name": "Jordan Magee", "team": "LAR" },
    { "name": "Ethan Driskell", "team": "CIN" },
    { "name": "Brevyn Spann-Ford", "team": "NE" },
    { "name": "Patrick McMorris", "team": "KC" },
    { "name": "Kamren Kinchens", "team": "LAR" },
    { "name": "Nick Correia", "team": "MIN" },
    { "name": "Demani Richardson", "team": "MIN" },
    { "name": "Khalid Duke", "team": "TB" },
    { "name": "Jarvis Brownlee Jr.", "team": "KC" },
    { "name": "Tanner McLachlan", "team": "WAS" },
    { "name": "Isaac Guerendo", "team": "LV" },
    { "name": "Tykee Smith", "team": "CIN" },
    { "name": "Grayson Murphy", "team": "PHI" },
    { "name": "Erick All", "team": "ARI" },
    { "name": "Joe Milton", "team": "CLE" },
    { "name": "Walter Rouse", "team": "BAL" },
    { "name": "Braelon Allen", "team": "LV" },
    { "name": "Xavier Thomas", "team": "MIN" },
    { "name": "Sam Hartman", "team": "SF" },
    { "name": "Michael Barrett", "team": "MIN" },
    { "name": "Tatum Bethune", "team": "DAL" },
    { "name": "Zion Tupuola-Fetui", "team": "IND" },
    { "name": "Brady Latham", "team": "SEA" },
    { "name": "Anim Dankwah", "team": "LV" },
    { "name": "Lideatrick Griffin", "team": "CIN" },
    { "name": "Tahj Washington", "team": "HOU" },
    { "name": "AJ Barner", "team": "NO" },
    { "name": "Zach Heins", "team": "CAR" },
    { "name": "Evan Williams", "team": "MIA" },
    { "name": "Jalyx Hunt", "team": "TEN" },
    { "name": "Trajan Jeffcoat", "team": "CLE" },
    { "name": "Jaden Crumedy", "team": "KC" },
    { "name": "Hunter Nourzad", "team": "LAC" },
    { "name": "Braiden McGregor", "team": "TB" },
    { "name": "Jaylon Carlies", "team": "HOU" },
    { "name": "Mohamed Kamara", "team": "BUF" },
    { "name": "Austin Reed", "team": "DET" },
    { "name": "Tayvion Robinson", "team": "MIN" },
    { "name": "Kitan Oladapo", "team": "SF" },
    { "name": "Luke McCaffrey", "team": "TEN" },
    { "name": "Nathan Thomas", "team": "GB" },
    { "name": "Easton Gibbs", "team": "LAR" },
    { "name": "Justin Eboigbe", "team": "GB" },
    { "name": "Elijah Jones", "team": "NYJ" },
    { "name": "Josh Proctor", "team": "NYJ" }
  ]
}
