[
  { "name": "Marvin Harrison Jr.", "team": "CHI" },
  { "name": "Caleb Williams", "team": "WAS" },
  { "name": "Drake Maye", "team": "NE" },
  { "name": "Malik Nabers", "team": "ARI" },
  { "name": "Nate Wiggins", "team": "LAC" },
  { "name": "Dallas Turner", "team": "NYG" },
  { "name": "Joe Alt", "team": "TEN" },
  { "name": "Demeioun Robinson", "team": "ATL" },
  { "name": "Brock Bowers", "team": "CHI" },
  { "name": "Jayden Daniels", "team": "NYJ" },
  { "name": "Michael Penix Jr.", "team": "MIN" },
  { "name": "Olumuyiwa Fashanu", "team": "DEN" },
  { "name": "Bo Nix", "team": "LV" },
  { "name": "Jer'Zhan Newton", "team": "NO" },
  { "name": "Graham Barton", "team": "IND" },
  { "name": "Laiatu Latu", "team": "SEA" },
  { "name": "Kool-Aid McKinstry", "team": "JAX" },
  { "name": "Trey Benson", "team": "CIN" },
  { "name": "Jared Verse", "team": "GB" },
  { "name": "Cooper DeJean", "team": "TB" },
  { "name": "Rome Odunze", "team": "ARI" },
  { "name": "Amarius Mims", "team": "LAR" },
  { "name": "Edgerrin Cooper", "team": "PIT" },
  { "name": "Taliese Fuaga", "team": "MIA" },
  { "name": "J.C. Latham", "team": "PHI" },
  { "name": "Keon Coleman", "team": "KC" },
  { "name": "Maason Smith", "team": "HOU" },
  { "name": "Terrion Arnold", "team": "DET" },
  { "name": "Brian Thomas Jr.", "team": "BUF" },
  { "name": "Jordan Morgan", "team": "DAL" },
  { "name": "Kamren Kinchens", "team": "SF" },
  { "name": "Kamari Lassiter", "team": "BAL" },
  { "name": "Bralen Trice", "team": "CAR" },
  { "name": "Troy Fautanu", "team": "WAS" },
  { "name": "Tyler Guyton", "team": "NE" },
  { "name": "J.T. Tuimoloau", "team": "ARI" },
  { "name": "Leonard Taylor", "team": "LAC" },
  { "name": "Adonai Mitchell", "team": "NYG" },
  { "name": "Xavier Legette", "team": "TEN" },
  { "name": "J.J. McCarthy", "team": "ATL" },
  { "name": "Chris Braswell", "team": "WAS" },
  { "name": "Tyler Nubin", "team": "GB" },
  { "name": "Kingsley Suamataia", "team": "MIN" },
  { "name": "Quinyon Mitchell", "team": "NO" },
  { "name": "Denzel Burke", "team": "LV" },
  { "name": "Josh Newton", "team": "PHI" },
  { "name": "Troy Franklin", "team": "IND" },
  { "name": "T'Vondre Sweat", "team": "NYG" },
  { "name": "Ja'Tavion Sanders", "team": "JAX" },
  { "name": "Jackson Powers-Johnson", "team": "CIN" },
  { "name": "Kiran Amegadjie", "team": "GB" },
  { "name": "Xavier Worthy", "team": "TB" },
  { "name": "Michael Hall Jr.", "team": "HOU" },
  { "name": "Kalen King", "team": "LAR" },
  { "name": "Kris Jenkins", "team": "PIT" },
  { "name": "Byron Murphy", "team": "MIA" },
  { "name": "Rod Moore", "team": "PHI" },
  { "name": "McKinnley Jackson", "team": "KC" },
  { "name": "Ruke Orhorhoro", "team": "CLE" },
  { "name": "Devontez Walker", "team": "DET" },
  { "name": "Brandon Dorlus", "team": "BUF" },
  { "name": "Ladd McConkey", "team": "DAL" },
  { "name": "Patrick Paul", "team": "SF" },
  { "name": "Calen Bullock", "team": "BAL" },
  { "name": "Ja'Lynn Polk", "team": "CAR" },
  { "name": "Javon Bullard", "team": "WAS" },
  { "name": "Caelen Carson", "team": "NE" },
  { "name": "TreVeyon Henderson", "team": "ARI" },
  { "name": "Adisa Isaac", "team": "LAC" },
  { "name": "Michael Pratt", "team": "NYG" },
  { "name": "Spencer Rattler", "team": "ARI" },
  { "name": "Tyler Davis", "team": "ATL" },
  { "name": "T.J. Tampa", "team": "CHI" },
  { "name": "Jeremiah Trotter Jr.", "team": "NYJ" },
  { "name": "Sedrick Van Pran", "team": "DET" },
  { "name": "Cooper Beebe", "team": "DEN" },
  { "name": "Zak Zinter", "team": "LV" },
  { "name": "Kris Abrams-Draine", "team": "SEA" },
  { "name": "Johnny Wilson", "team": "IND" },
  { "name": "Braden Fiske", "team": "SEA" },
  { "name": "Jonah Elliss", "team": "JAX" },
  { "name": "Zach Frazier", "team": "CIN" },
  { "name": "Blake Corum", "team": "GB" },
  { "name": "Ricky Pearsall", "team": "TB" },
  { "name": "D.J. James", "team": "ARI" },
  { "name": "Malachi Corley", "team": "LAR" },
  { "name": "Anthony Belton", "team": "PIT" },
  { "name": "Ennis Rakestraw Jr.", "team": "HOU" },
  { "name": "Justin Walley", "team": "KC" },
  { "name": "Cedric Gray", "team": "CLE" },
  { "name": "Darius Robinson", "team": "DET" },
  { "name": "Tykee Smith", "team": "GB" },
  { "name": "Johnny Dixon", "team": "DAL" },
  { "name": "Cade Stover", "team": "WAS" },
  { "name": "Mar'Keise Irving", "team": "BAL" },
  { "name": "Payton Wilson", "team": "CAR" },
  { "name": "Tommy Eichenberg", "team": "WAS" },
  { "name": "J.Michael Sturdivant", "team": "NE" },
  { "name": "Christian Haynes", "team": "ARI" },
  { "name": "Will Shipley", "team": "LAC" },
  { "name": "Max Melton", "team": "NYG" },
  { "name": "Donovan Jackson", "team": "TEN" },
  { "name": "Cam Hart", "team": "ATL" },
  { "name": "Quinn Ewers", "team": "CHI" },
  { "name": "Christian Mahogany", "team": "NYJ" },
  { "name": "Braelon Allen", "team": "MIN" },
  { "name": "Jermaine Burton", "team": "NYJ" },
  { "name": "Mekhi Wingo", "team": "LV" },
  { "name": "Jonathon Brooks", "team": "NO" },
  { "name": "Cole Bishop", "team": "IND" },
  { "name": "Dominick Puni", "team": "SEA" },
  { "name": "Brenden Rice", "team": "ATL" },
  { "name": "DeWayne Carter", "team": "CIN" },
  { "name": "Marist Liufau", "team": "GB" },
  { "name": "Matt Goncalves", "team": "TB" },
  { "name": "Audric Estime", "team": "HOU" },
  { "name": "Marshawn Kneeland", "team": "PIT" },
  { "name": "Khyree Jackson", "team": "PIT" },
  { "name": "Mohamed Kamara", "team": "DEN" },
  { "name": "Blake Fisher", "team": "CHI" },
  { "name": "James Williams", "team": "KC" },
  { "name": "Gabriel Murphy", "team": "HOU" },
  { "name": "Nelson Ceaser", "team": "MIN" },
  { "name": "Jalen McMillan", "team": "BUF" },
  { "name": "Jaheim Bell", "team": "SF" },
  { "name": "Layden Robinson", "team": "SF" },
  { "name": "Roman Wilson", "team": "BAL" },
  { "name": "Donovan Edwards", "team": "CLE" },
  { "name": "Marcellas Dial", "team": "WAS" },
  { "name": "Chau Smith-Wade", "team": "NE" },
  { "name": "Javon Foster", "team": "CLE" },
  { "name": "Ty'Ron Hopper", "team": "LAC" },
  { "name": "Zemaiah Vaughn", "team": "NYG" },
  { "name": "M.J. Devonshire", "team": "CAR" },
  { "name": "Kamal Hadden", "team": "ATL" },
  { "name": "MarShawn Lloyd", "team": "CHI" },
  { "name": "Jordan Travis", "team": "DEN" },
  { "name": "Kaden Prather", "team": "TEN" },
  { "name": "Gabe Hall", "team": "DEN" },
  { "name": "Junior Colson", "team": "LV" },
  { "name": "Zion Tupuola-Fetui", "team": "NO" },
  { "name": "Cedric Johnson", "team": "IND" },
  { "name": "Jasheen Davis", "team": "SEA" },
  { "name": "Mike Sainristil", "team": "JAX" },
  { "name": "Ainias Smith", "team": "CIN" },
  { "name": "Jaden Hicks", "team": "BUF" },
  { "name": "Julian Pearl", "team": "TEN" },
  { "name": "Beau Brade", "team": "ARI" },
  { "name": "Hudson Clark", "team": "LAR" },
  { "name": "Josh Proctor", "team": "LAR" },
  { "name": "Brandon Coleman", "team": "MIA" },
  { "name": "J.C. Davis", "team": "ARI" },
  { "name": "Jacob Cowing", "team": "KC" },
  { "name": "Andru Phillips", "team": "MIN" },
  { "name": "Jaylan Ford", "team": "DET" },
  { "name": "Dillon Johnson", "team": "BUF" },
  { "name": "Javion Cohen", "team": "KC" },
  { "name": "Dallin Holker", "team": "CAR" },
  { "name": "Shemar Turner", "team": "BAL" },
  { "name": "Christian Jones", "team": "JAX" },
  { "name": "Isheem Young", "team": "WAS" },
  { "name": "Jawhar Jordan", "team": "NE" },
  { "name": "Ray Davis", "team": "CAR" },
  { "name": "Isaiah Adams", "team": "LAC" },
  { "name": "Sione Vaki", "team": "NYG" },
  { "name": "Xavier Thomas", "team": "TEN" },
  { "name": "Ben Sinnott", "team": "TEN" },
  { "name": "Roger Rosengarten", "team": "MIA" },
  { "name": "Jamari Thrash", "team": "NYJ" },
  { "name": "Justin Eboigbe", "team": "MIN" },
  { "name": "Cameron Ward", "team": "LAR" },
  { "name": "Javon Solomon", "team": "NE" },
  { "name": "Malik Washington", "team": "NO" },
  { "name": "Jaylin Simpson", "team": "IND" },
  { "name": "Tatum Bethune", "team": "SEA" },
  { "name": "Sataoa Laumea", "team": "JAX" },
  { "name": "Theo Johnson", "team": "CIN" },
  { "name": "Elijhah Badger", "team": "GB" },
  { "name": "Trevin Wallace", "team": "TB" },
  { "name": "Sheridan Jones", "team": "CLE" },
  { "name": "Ja'Quan Sheppard", "team": "BUF" },
  { "name": "Keith Randolph Jr.", "team": "PIT" },
  { "name": "Dwight McGlothern", "team": "MIA" },
  { "name": "Drake Nugent", "team": "NO" },
  { "name": "Renardo Green", "team": "LV" },
  { "name": "Andrew Coker", "team": "ATL" },
  { "name": "Khordae Sydnor", "team": "DET" },
  { "name": "Desmond Evans", "team": "BUF" },
  { "name": "Frank Gore Jr.", "team": "DAL" },
  { "name": "Xavier Watts", "team": "DEN" },
  { "name": "Tyrice Knight", "team": "CLE" },
  { "name": "Storm Duck", "team": "TEN" },
  { "name": "Kitan Oladapo", "team": "WAS" },
  { "name": "Beaux Limmer", "team": "LV" },
  { "name": "Kalen DeLoach", "team": "HOU" },
  { "name": "Joshua Gray", "team": "LAC" },
  { "name": "Jaden Crumedy", "team": "ARI" },
  { "name": "Bryson Nesbit", "team": "LV" },
  { "name": "Moose Muhammad III", "team": "CLE" },
  { "name": "Brennan Jackson", "team": "NE" },
  { "name": "Jahdae Barron", "team": "BAL" },
  { "name": "Maxwell Hairston", "team": "LV" },
  { "name": "Tez Johnson", "team": "SF" },
  { "name": "Evan Williams", "team": "DAL" },
  { "name": "Bub Means", "team": "HOU" },
  { "name": "Andrew Raym", "team": "IND" },
  { "name": "Joe Milton", "team": "SEA" },
  { "name": "Cody Schrader", "team": "JAX" },
  { "name": "Edefuan Ulofoshio", "team": "CIN" },
  { "name": "Jaden Davis", "team": "GB" },
  { "name": "Gavin Hardison", "team": "TB" },
  { "name": "Zion Nelson", "team": "HOU" },
  { "name": "Sam Wiglusz", "team": "DEN" },
  { "name": "Dylan Laube", "team": "PIT" },
  { "name": "Jared Wiley", "team": "MIA" },
  { "name": "Sean Martin", "team": "TEN" },
  { "name": "Ladarius Henderson", "team": "HOU" },
  { "name": "Antwaun Powell-Ryland", "team": "ARI" },
  { "name": "Omar Speights", "team": "DET" },
  { "name": "Garret Greenfield", "team": "BUF" },
  { "name": "Malik Mustapha", "team": "DAL" },
  { "name": "Jarrian Jones", "team": "SF" },
  { "name": "Dylan McMahon", "team": "BAL" }
]
