{
  "players": [
    { "name": "Caleb Williams", "team": "Bears" },
    { "name": "Drake Maye", "team": "Commanders" },
    { "name": "Jayden Daniels", "team": "Patriots" },
    { "name": "Marvin Harrison Jr.", "team": "Cardinals" },
    { "name": "Malik Nabers", "team": "Chargers" },
    { "name": "Brock Bowers", "team": "Giants" },
    { "name": "Joe Alt", "team": "Titans" },
    { "name": "Olumuyiwa Fashanu", "team": "Falcons" },
    { "name": "Jared Verse", "team": "Bears" },
    { "name": "Rome Odunze", "team": "Jets" },
    { "name": "Dallas Turner", "team": "Vikings" },
    { "name": "Michael Penix Jr.", "team": "Broncos" },
    { "name": "Amarius Mims", "team": "Raiders" },
    { "name": "Chop Robinson", "team": "Saints" },
    { "name": "Troy Franklin", "team": "Colts" },
    { "name": "Terrion Arnold", "team": "Seahawks" },
    { "name": "Quinyon Mitchell", "team": "Jaguars" },
    { "name": "Jer'Zhan Newton", "team": "Bengals" },
    { "name": "Troy Fautanu", "team": "Rams" },
    { "name": "Koo", "team": "Steelers" },
    { "name": "Tyler Guyton", "team": "Dolphins" },
    { "name": "Taliese Fuaga", "team": "Eagles" },
    { "name": "Cooper DeJean", "team": "Vikings" },
    { "name": "Jackson Power", "team": "Cowboys" },
    { "name": "Nate Wiggins", "team": "Packers" },
    { "name": "Brian Thomas Jr.", "team": "Buccaneers" },
    { "name": "JC Latham", "team": "Cardinals" },
    { "name": "Xavier Worthy", "team": "Bills" },
    { "name": "Kamari Lassiter", "team": "Lions" },
    { "name": "Edgerrin Cooper", "team": "Ravens" },
    { "name": "Kalen King", "team": "49ers" },
    { "name": "Ladd McConkey", "team": "Chiefs" },
    { "name": "Keon Coleman", "team": "Panthers" },
    { "name": "Kingsley Suamataia", "team": "Patriots" },
    { "name": "Laiatu Latu", "team": "Cardinals" },
    { "name": "Graham Barton", "team": "Commanders" },
    { "name": "Byron Murphy", "team": "Chargers" },
    { "name": "Ja'Lynn Polk", "team": "Titans" },
    { "name": "Bralen Trice", "team": "Panthers" },
    { "name": "Ja'Tavion Sanders", "team": "Commanders" },
    { "name": "Jordan Morgan", "team": "Packers" },
    { "name": "Maason Smith", "team": "Texans" },
    { "name": "JJ McCarthy", "team": "Falcons" },
    { "name": "Ennis Rakestraw Jr.", "team": "Raiders" },
    { "name": "Adonai Mitchell", "team": "Saints" },
    { "name": "DJ James", "team": "Colts" },
    { "name": "Bo Nix", "team": "Giants" },
    { "name": "Patrick Paul", "team": "Jaguars" },
    { "name": "Caelen Carson", "team": "Bengals" },
    { "name": "Leonard Taylor", "team": "Eagles" },
    { "name": "Tyler Nubin", "team": "Steelers" },
    { "name": "Chris Braswell", "team": "Rams" },
    { "name": "Kamren Kinchens", "team": "Eagles" },
    { "name": "T'Vondre Sweat", "team": "Browns" },
    { "name": "T.J. Tampa", "team": "Dolphins" },
    { "name": "Jonathan Brooks", "team": "Cowboys" },
    { "name": "Cooper Beebe", "team": "Packers" },
    { "name": "Kiran Amegadjie", "team": "Buccaneers" },
    { "name": "Zion Tupuol", "team": "Texans" },
    { "name": "Zach Frazier", "team": "Bills" },
    { "name": "Devontez Walker", "team": "Lions" },
    { "name": "Kris Jenkins", "team": "Ravens" },
    { "name": "Blake Fisher", "team": "49ers" },
    { "name": "Braden Fiske", "team": "Chiefs" },
    { "name": "Josh Newton", "team": "Panthers" },
    { "name": "Kris Abram", "team": "Cardinals" },
    { "name": "Javon Bullard", "team": "Commanders" },
    { "name": "Roman Wilson", "team": "Patriots" },
    { "name": "Adisa Isaac", "team": "Chargers" },
    { "name": "Xavier Legette", "team": "Giants" },
    { "name": "Tyler Davis", "team": "Cardinals" },
    { "name": "Max Melton", "team": "Jets" },
    { "name": "Jonah Elliss", "team": "Lions" },
    { "name": "Sedrick Van Pran", "team": "Falcons" },
    { "name": "Jeremiah Trotter Jr.", "team": "Bears" },
    { "name": "Braelon Allen", "team": "Broncos" },
    { "name": "Christian Haynes", "team": "Raiders" },
    { "name": "Zak Zinter", "team": "Commanders" },
    { "name": "Michael Hall", "team": "Falcons" },
    { "name": "Ricky Pearsall", "team": "Bengals" },
    { "name": "Ruke Orhorhoro", "team": "Seahawks" },
    { "name": "Cade Stover", "team": "Colts" },
    { "name": "Jermaine Burton", "team": "Rams" },
    { "name": "Marist Liufau", "team": "Steelers" },
    { "name": "Matt Goncalves", "team": "Browns" },
    { "name": "Malachi Corley", "team": "Texans" },
    { "name": "Mike Sainristil", "team": "Cowboys" },
    { "name": "Khyree Jackson", "team": "Packers" },
    { "name": "Cam Hart", "team": "Buccaneers" },
    { "name": "Trey Benson", "team": "Cardinals" },
    { "name": "Christian Mahogany", "team": "Packers" },
    { "name": "Blake Corum", "team": "Buccaneers" },
    { "name": "Audric Estime", "team": "Ravens" },
    { "name": "Layden Robinson", "team": "49ers" },
    { "name": "Anthony Belton", "team": "Chiefs" },
    { "name": "Payton Wilson", "team": "Jaguars" },
    { "name": "Will Shipley", "team": "Bengals" },
    { "name": "Isaiah Adams", "team": "Steelers" },
    { "name": "Calen Bullock", "team": "Rams" },
    { "name": "Brandon Dorlus", "team": "Commanders" },
    { "name": "Bucky Irving", "team": "Panthers" },
    { "name": "Gabriel Murphy", "team": "Seahawks" },
    { "name": "Cedric Gray", "team": "Patriots" },
    { "name": "Tanor Bortolini", "team": "Cardinals" },
    { "name": "Delmar Glaze", "team": "Chargers" },
    { "name": "Mohamed Kamara", "team": "Titans" },
    { "name": "Dominick Puni", "team": "Giants" },
    { "name": "Marshawn Lloyd", "team": "Vikings" },
    { "name": "Brenden Rice", "team": "Falcons" },
    { "name": "Jaheim Bell", "team": "Chargers" },
    { "name": "Roger Rosengarten", "team": "Jets" },
    { "name": "Mekhi Wingo", "team": "Raiders" },
    { "name": "Johnny Wilson", "team": "Ravens" },
    { "name": "Keith Randolph Jr.", "team": "Jaguars" },
    { "name": "Junior Colson", "team": "Bengals" },
    { "name": "Javion Cohen", "team": "Jaguars" },
    { "name": "Beau Brade", "team": "Colts" },
    { "name": "Jalen McMillian", "team": "Seahawks" },
    { "name": "Javon Foster", "team": "Steelers" },
    { "name": "Devaughn Vele", "team": "Eagles" },
    { "name": "McKinnley Jackson", "team": "Broncos" },
    { "name": "Julian Pearl", "team": "Bears" },
    { "name": "Kamal Hadden", "team": "Texans" },
    { "name": "Tommy Eichenberg", "team": "49ers" },
    { "name": "Joe Milton", "team": "Packers" },
    { "name": "Cole Bishop", "team": "Buccaneers" },
    { "name": "Sataoa Laumea", "team": "Texans" },
    { "name": "Jawhar Jordan", "team": "Bills" },
    { "name": "Jamari Thrash", "team": "Vikings" },
    { "name": "Johnny Dixon", "team": "Ravens" },
    { "name": "James Williams", "team": "Chiefs" },
    { "name": "Javon Baker", "team": "49ers" },
    { "name": "Michael Pratt", "team": "Bills" },
    { "name": "Justin Eboigbe", "team": "Jets" },
    { "name": "Jaden Hicks", "team": "49ers" },
    { "name": "Ray Davis", "team": "Broncos" },
    { "name": "Nelson Ceaser", "team": "Patriots" },
    { "name": "Malik Washington", "team": "Cardinals" },
    { "name": "Javon Solomon", "team": "Commanders" },
    { "name": "Jacob Cowing", "team": "Chargers" },
    { "name": "Marcellas Dial", "team": "Giants" },
    { "name": "Erick All", "team": "Panthers" },
    { "name": "Tykee Smith", "team": "Falcons" },
    { "name": "Cody Schrader", "team": "Bills" },
    { "name": "Ainias Smith", "team": "Broncos" },
    { "name": "Jordan Travis", "team": "Titans" },
    { "name": "Spencer Rattler", "team": "Broncos" },
    { "name": "Curtis Jacobs", "team": "Raiders" },
    { "name": "Kitan Oladapo", "team": "Bengals" },
    { "name": "Josh Proctor", "team": "Saints" },
    { "name": "Christian Jones", "team": "Colts" },
    { "name": "Brandon Coleman", "team": "Commanders" },
    { "name": "Ben Sinnott", "team": "Jaguars" },
    { "name": "Chau Smit", "team": "Rams" },
    { "name": "JD Bertrand", "team": "Rams" },
    { "name": "Beaux Limmer", "team": "Browns" },
    { "name": "Dillon Johnson", "team": "Vikings" },
    { "name": "Braiden Mcgregor", "team": "Dolphins" },
    { "name": "Kimani Vidal", "team": "Chiefs" },
    { "name": "Walter Rouse", "team": "Bills" },
    { "name": "Xavier Thomas", "team": "Eagles" },
    { "name": "Sheridan Jones", "team": "Cardinals" },
    { "name": "Dominique Hampton", "team": "Bills" },
    { "name": "Ty'Ron Hopper", "team": "Lions" },
    { "name": "Zion Nelson", "team": "Ravens" },
    { "name": "Kenny Logan Jr.", "team": "Panthers" },
    { "name": "Isaac Guerendo", "team": "Vikings" },
    { "name": "Kendall Milton", "team": "Saints" },
    { "name": "Jaylan Ford", "team": "Packers" },
    { "name": "Myles Harden", "team": "Saints" },
    { "name": "Micah Abraham", "team": "Eagles" },
    { "name": "Taulia Tagovailoa", "team": "Eagles" },
    { "name": "Grayson Murphy", "team": "Chiefs" },
    { "name": "Isaiah Williams", "team": "Cowboys" },
    { "name": "DeWayne Carter", "team": "Saints" },
    { "name": "Trevin Wallace", "team": "49ers" },
    { "name": "Drake Nugent", "team": "Vikings" },
    { "name": "Miyan Williams", "team": "Steelers" },
    { "name": "Kingsley Eguakun", "team": "Seahawks" },
    { "name": "Myles Jones", "team": "Patriots" },
    { "name": "Tatum Bethune", "team": "Chargers" },
    { "name": "Cedric Johnson", "team": "Titans" },
    { "name": "Gabe Hall", "team": "Giants" },
    { "name": "Jake Briningstool", "team": "Dolphins" },
    { "name": "Myles Cole", "team": "Jets" },
    { "name": "Sam Hartman", "team": "Cardinals" },
    { "name": "Joshua Gray", "team": "Eagles" },
    { "name": "Jaylen Wright", "team": "Texans" },
    { "name": "Zy Alexander", "team": "Rams" },
    { "name": "Roman Hemby", "team": "Saints" },
    { "name": "Brennan Jackson", "team": "Colts" },
    { "name": "MJ Devonshire", "team": "Seahawks" },
    { "name": "Darius Robinson", "team": "Patriots" },
    { "name": "Jeremy Flax", "team": "Bengals" },
    { "name": "Marshawn Kneeland", "team": "Steelers" },
    { "name": "Storm Duck", "team": "Bills" },
    { "name": "Brevyn Span", "team": "Falcons" },
    { "name": "Jordan Whittington", "team": "Dolphins" },
    { "name": "Brant Kuithe", "team": "Saints" },
    { "name": "Khristian Boyd", "team": "Bills" },
    { "name": "Jase McClellan", "team": "Packers" },
    { "name": "Sione Vaki", "team": "Lions" },
    { "name": "Dallas Gant", "team": "Broncos" },
    { "name": "Akeem Dent", "team": "Bills" },
    { "name": "Dallin Holker", "team": "Lions" },
    { "name": "Luke McCaffrey", "team": "Browns" },
    { "name": "Andrew Raym", "team": "Broncos" },
    { "name": "Frank Gore Jr.", "team": "Raiders" },
    { "name": "Ja'Quan Sheppard", "team": "Rams" },
    { "name": "Nehemiah Pritchett", "team": "Eagles" },
    { "name": "Omar Speights", "team": "49ers" },
    { "name": "Brian Ugwu", "team": "Jaguars" },
    { "name": "Fentrell Cypress", "team": "Rams" },
    { "name": "Andrew Coker", "team": "Bengals" },
    { "name": "Malik Mustapha", "team": "49ers" },
    { "name": "Xavier Watts", "team": "Cowboys" },
    { "name": "Dylan McMahon", "team": "Rams" },
    { "name": "Austin Booker", "team": "Ravens" },
    { "name": "Moose Muhammad III", "team": "Packers" },
    { "name": "David Ugwoegbu", "team": "Buccaneers" },
    { "name": "Charles Turner III", "team": "Titans" },
    { "name": "Rasheen Ali", "team": "Commanders" },
    { "name": "Theo Johnson", "team": "Raiders" },
    { "name": "Jah Joyner", "team": "Bengals" },
    { "name": "Jaylin Simpson", "team": "Chargers" },
    { "name": "Gavin Bartholomew", "team": "Cardinals" },
    { "name": "Evan Williams", "team": "Raiders" },
    { "name": "Marcus Rosem", "team": "Ravens" },
    { "name": "Jaden Davis", "team": "Raiders" },
    { "name": "Michael Wiley", "team": "Browns" },
    { "name": "Hudson Clark", "team": "Patriots" },
    { "name": "Edefuan Ulofoshio", "team": "Vikings" },
    { "name": "Ethan Driskell", "team": "Cowboys" },
    { "name": "Eric Watts", "team": "Colts" },
    { "name": "Devin Kirkwood", "team": "Seahawks" },
    { "name": "Aubrey Burks", "team": "Jaguars" },
    { "name": "Tory Taylor", "team": "Bengals" },
    { "name": "Gavin Hardison", "team": "Texans" },
    { "name": "Caedan Wallace", "team": "Saints" },
    { "name": "Quincy Riley", "team": "Panthers" },
    { "name": "Noah Daniels", "team": "Dolphins" },
    { "name": "Trey Knox", "team": "Chiefs" },
    { "name": "Zakhari Franklin", "team": "Vikings" },
    { "name": "Xavier Weaver", "team": "Cowboys" },
    { "name": "Jaylen Harrell", "team": "Packers" },
    { "name": "Ron Stone Jr.", "team": "Buccaneers" },
    { "name": "Daequan Hardy", "team": "Texans" },
    { "name": "Dominic Lovett", "team": "Bills" },
    { "name": "LaMiles Brooks", "team": "Lions" },
    { "name": "Jaylon Carlies", "team": "Ravens" },
    { "name": "Dwight McFlothern", "team": "49ers" },
    { "name": "Ladarius Henderson", "team": "Titans" },
    { "name": "Nathan Thomas", "team": "Chargers" },
    { "name": "Brennan Armstrong", "team": "Rams" },
    { "name": "Tip Reiman", "team": "Packers" },
    { "name": "Renardo Green", "team": "Jets" },
    { "name": "Daijun Edwards", "team": "Jets" }
  ],
  "pickedFor": "Vikings"
}
